Workbook

Sheet Executive Summary
A1: Suzuki Motor Corporation — Executive Summary
A2: FY2024 Financial Performance Review | Analysis Date: July 2026
A4: Overall Verdict: MIXED — IN LINE WITH PEERS
A6: Key Takeaways
A7: Growth | B7: Revenue grew 8.0% YoY to $37.1B, outpacing the prior year and reflecting continued demand strength.
A8: Profitability | B8: Net margin improved slightly from 4.8% to 5.0% — modest but consistent with typical auto industry margins.
A9: Returns | B9: ROE of 9.2% is roughly in line with Honda (9.7%) but notably below Toyota (15.7%) for the same fiscal year.
A10: Leverage | B10: Debt-to-Equity declined from 0.82x to 0.72x — a genuinely positive, de-risking trend independent of the profitability picture.
A11: Liquidity | B11: Current Ratio eased slightly from 1.47x to 1.40x but remains healthy and above the 1.0x safety threshold.
A12: Cash Generation | B12: Free Cash Flow rose 19.0% to $4.48B, strengthening the balance sheet and funding capacity.
A14: Bottom Line
A15: Suzuki's FY2024 results show genuine improvement in revenue growth, leverage reduction, and free cash flow generation, but profitability (Net Margin, ROE, ROA) remains modest and below Toyota's on a like-for-like basis, while roughly matching Honda's. This is a more typical picture for an automotive manufacturer than an outperformance story — Suzuki's real strength this year lies in balance sheet discipline (falling leverage) and cash generation, not in industry-leading returns. See the Ratio Analysis, DuPont Analysis, and Peer Benchmarking sheets for full supporting detail.

Sheet Summary Dashboard
A1: Suzuki Motor Corporation — Financial Ratio Analysis Dashboard
A2: FY2024 vs FY2023 performance, based on consolidated financial statements.
A4: Key Ratios Snapshot
A5: Ratio | B5: FY2024 | C5: FY2023 | D5: YoY Change
A6: Current Ratio | B6: ='Ratio Analysis'!C6 -> 1.4000992 | C6: ='Ratio Analysis'!D6 -> 1.4713351 | D6: =B6-C6 -> -0.071235914
A7: Gross Profit Margin | B7: ='Ratio Analysis'!C8 -> 0.26561324 | C7: ='Ratio Analysis'!D8 -> 0.25356512 | D7: =B7-C7 -> 0.012048127
A8: Net Profit Margin | B8: ='Ratio Analysis'!C9 -> 0.049814602 | C8: ='Ratio Analysis'!D9 -> 0.04763 | D8: =B8-C8 -> 0.0021846017
A9: EPS | B9: ='Ratio Analysis'!C16 -> 3.82 | C9: ='Ratio Analysis'!D16 -> 3.37 | D9: =B9-C9 -> 0.45
A11: FY2024 Snapshot (Return & Efficiency)
A12: Metric | B12: FY2024
A13: Return on Equity (ROE) | B13: ='Ratio Analysis'!C10 -> 0.091859688
A14: Return on Assets (ROA) | B14: ='Ratio Analysis'!C11 -> 0.052008669
A15: Asset Turnover | B15: ='Ratio Analysis'!C13 -> 1.0440447
A16: Inventory Turnover | B16: ='Ratio Analysis'!C14 -> 7.0967005
A19: Revenue & Profitability Trend ($ millions)
A20: Metric | B20: FY2024 | C20: FY2023
A21: Revenue | B21: ='Income Statement'!B5 -> 37082.3 | C21: ='Income Statement'!C5 -> 34348.1
A22: Gross Profit | B22: ='Income Statement'!B7 -> 9849.55 | C22: ='Income Statement'!C7 -> 8709.48
A23: Operating Income | B23: ='Income Statement'!B12 -> 4002.32 | C23: ='Income Statement'!C12 -> 2788.25
A24: Net Income | B24: ='Income Statement'!B18 -> 1847.24 | C24: ='Income Statement'!C18 -> 1636

Sheet 5-Year Trend
A1: Suzuki Motor Corporation — 5-Year Revenue & Net Income Trend
A2: FY2020–FY2024 (fiscal years ended March 31). Sourced from company filings via StockAnalysis.com / MacroTrends.
A4: Fiscal Year | B4: Revenue ($M) | C4: Net Income ($M) | D4: Net Margin | E4: Revenue YoY Growth
A5: FY2020 | B5: 32094 | C5: 1235 | D5: =C5/B5 -> 0.038480713 | E5: —
A6: FY2021 | B6: 29875 | C6: 1376 | D6: =C6/B6 -> 0.046058577 | E6: =(B6-B5)/B5 -> -0.069140649
A7: FY2022 | B7: 31759 | C7: 1427 | D7: =C7/B7 -> 0.044932145 | E7: =(B7-B6)/B6 -> 0.063062762
A8: FY2023 | B8: 34348 | C8: 1636 | D8: =C8/B8 -> 0.047630139 | E8: =(B8-B7)/B7 -> 0.081520199
A9: FY2024 | B9: 37082 | C9: 1847 | D9: =C9/B9 -> 0.049808532 | E9: =(B9-B8)/B8 -> 0.079597065
A11: Observation
A12: Revenue dipped in FY2021 (COVID-19 demand shock) before recovering steadily through FY2024, growing at a compound annual growth rate of roughly 4.5% over the 5-year window. Net income has grown more consistently than revenue every year in this period, including through the FY2021 downturn — indicating steady underlying cost discipline even during the pandemic-affected year.

Sheet Ratio Analysis
A1: Suzuki Motor Corporation — Financial Ratio Analysis
A2: All ratios calculated via live formulas referencing the Balance Sheet and Income Statement sheets.
A4: Ratio | B4: Formula | C4: FY2024 | D4: FY2023 | E4: Interpretation
A5: LIQUIDITY
A6: Current Ratio | B6: Total Current Assets / Total Current Liabilities | C6: ='Balance Sheet'!B11/'Balance Sheet'!B22 -> 1.4000992 | D6: ='Balance Sheet'!C11/'Balance Sheet'!C22 -> 1.4713351 | E6: Measures short-term ability to cover current liabilities with current assets.
A7: PROFITABILITY
A8: Gross Profit Margin | B8: Gross Profit / Revenue | C8: ='Income Statement'!B7/'Income Statement'!B5 -> 0.26561324 | D8: ='Income Statement'!C7/'Income Statement'!C5 -> 0.25356512 | E8: Percentage of revenue retained after direct production costs.
A9: Net Profit Margin | B9: Net Income / Revenue | C9: ='Income Statement'!B18/'Income Statement'!B5 -> 0.049814602 | D9: ='Income Statement'!C18/'Income Statement'!C5 -> 0.04763 | E9: Percentage of revenue converted into bottom-line profit.
A10: Return on Equity (ROE) | B10: Net Income / Average Shareholders Equity | C10: ='Income Statement'!B18/(('Balance Sheet'!B32+'Balance Sheet'!C32)/2) -> 0.091859688 | D10: N/A* | E10: Return generated on shareholders' invested capital.
A11: Return on Assets (ROA) | B11: Net Income / Average Total Assets | C11: ='Income Statement'!B18/(('Balance Sheet'!B20+'Balance Sheet'!C20)/2) -> 0.052008669 | D11: N/A* | E11: How efficiently total assets are converted into profit.
A12: EFFICIENCY
A13: Asset Turnover | B13: Revenue / Average Total Assets | C13: ='Income Statement'!B5/(('Balance Sheet'!B20+'Balance Sheet'!C20)/2) -> 1.0440447 | D13: N/A* | E13: How efficiently assets generate sales revenue.
A14: Inventory Turnover | B14: COGS / Average Inventory | C14: ='Income Statement'!B6/(('Balance Sheet'!B8+'Balance Sheet'!C8)/2) -> 7.0967005 | D14: N/A* | E14: How many times inventory is sold and replaced in the period.
A15: PER-SHARE
A16: Earnings Per Share (EPS) | B16: Net Income / Shares Outstanding | C16: ='Income Statement'!B22 -> 3.82 | D16: ='Income Statement'!C22 -> 3.37 | E16: Profit attributable to each outstanding share.
A17: LIQUIDITY (CONT.)
A18: Quick Ratio (Acid-Test) | B18: (Total Current Assets − Inventory) / Total Current Liabilities | C18: =('Balance Sheet'!B11-'Balance Sheet'!B8)/'Balance Sheet'!B22 -> 1.0602111 | D18: =('Balance Sheet'!C11-'Balance Sheet'!C8)/'Balance Sheet'!C22 -> 1.1450337 | E18: Stricter liquidity test excluding inventory from current assets.
A19: LEVERAGE
A20: Debt-to-Equity | B20: Total Liabilities / Total Shareholders Equity | C20: ='Balance Sheet'!B26/'Balance Sheet'!B32 -> 0.71604077 | D20: ='Balance Sheet'!C26/'Balance Sheet'!C32 -> 0.82479278 | E20: Proportion of debt financing relative to shareholders' equity.
A21: Debt-to-Assets | B21: Total Liabilities / Total Assets | C21: ='Balance Sheet'!B26/'Balance Sheet'!B20 -> 0.41726315 | D21: ='Balance Sheet'!C26/'Balance Sheet'!C20 -> 0.45199244 | E21: Proportion of total assets financed through debt.
A22: Equity Multiplier | B22: Total Assets / Total Shareholders Equity | C22: ='Balance Sheet'!B20/'Balance Sheet'!B32 -> 1.7160412 | D22: ='Balance Sheet'!C20/'Balance Sheet'!C32 -> 1.8247933 | E22: Degree of financial leverage — higher values indicate greater reliance on debt.
A23: CASH FLOW
A24: Operating Cash Flow Ratio | B24: Cash Flow from Operations / Total Current Liabilities | C24: ='Cash Flow Statement'!B12/'Balance Sheet'!B22 -> 0.54527054 | D24: ='Cash Flow Statement'!C12/'Balance Sheet'!C22 -> 0.54125182 | E24: Ability to cover current liabilities using cash generated from operations.
A25: Cash Flow Margin | B25: Cash Flow from Operations / Revenue | C25: ='Cash Flow Statement'!B12/'Income Statement'!B5 -> 0.17664641 | D25: ='Cash Flow Statement'!C12/'Income Statement'!C5 -> 0.173447 | E25: Percentage of revenue converted into operating cash flow.
A26: Free Cash Flow ($M) | B26: Cash Flow from Operations − Capital Expenditures | C26: ='Cash Flow Statement'!B12+'Cash Flow Statement'!B13 -> 4483.712 | D26: ='Cash Flow Statement'!C12+'Cash Flow Statement'!C13 -> 3766.52 | E26: Cash remaining after reinvestment in property, plant & equipment.
A28: *FY2023 figures requiring average balances (ROE, ROA, Asset Turnover, Inventory Turnover) are not shown, as they would require FY2022 balance sheet data not available in this dataset.

Sheet DuPont Analysis
A1: DuPont Analysis — ROE Decomposition (FY2024)
A2: Breaks Return on Equity into three drivers: profitability, efficiency, and leverage.
A4: Component
A5: Net Profit Margin | B5: Net Income / Revenue | C5: ='Income Statement'!B18/'Income Statement'!B5 -> 0.049814602
A6: × Asset Turnover | B6: Revenue / Average Total Assets | C6: ='Income Statement'!B5/(('Balance Sheet'!B20+'Balance Sheet'!C20)/2) -> 1.0440447
A7: × Equity Multiplier | B7: Average Total Assets / Average Shareholders Equity | C7: =(('Balance Sheet'!B20+'Balance Sheet'!C20)/2)/(('Balance Sheet'!B32+'Balance Sheet'!C32)/2) -> 1.766238
A8: Return on Equity (ROE) | B8: Product of the three components above | C8: =C5*C6*C7 -> 0.091859688
A10: Cross-check: Direct ROE (Net Income / Average Equity) | C10: ='Income Statement'!B18/(('Balance Sheet'!B32+'Balance Sheet'!C32)/2) -> 0.091859688
A13: Interpretation
A14: Suzuki's FY2024 ROE is driven primarily by strong net profit margin and a meaningful equity multiplier (financial leverage), with asset turnover contributing a smaller but positive effect. This indicates returns are being generated through a combination of profitability and balance sheet leverage, rather than asset efficiency alone.

Sheet Peer Benchmarking
A1: Peer Benchmarking — Suzuki vs. Toyota vs. Honda (FY2024)
A2: FY2024 (fiscal year ended March 31, 2024) ratios compared across three major Japanese automotive manufacturers.
A4: Ratio | B4: Suzuki | C4: Toyota | D4: Honda | E4: Industry Avg | F4: Suzuki vs. Peers
A5: Current Ratio | B5: ='Ratio Analysis'!C6 -> 1.4000992 | C5: 1.19 | D5: 1.43 | E5: =AVERAGE(C5:D5) -> 1.31 | F5: =IF(B5>E5,"Above Peer Avg","Below Peer Avg") -> Above Peer Avg
A6: Quick Ratio | B6: ='Ratio Analysis'!C18 -> 1.0602111 | C6: 0.83 | D6: 1.08 | E6: =AVERAGE(C6:D6) -> 0.955 | F6: =IF(B6>E6,"Above Peer Avg","Below Peer Avg") -> Above Peer Avg
A7: Asset Turnover | B7: ='Ratio Analysis'!C13 -> 1.0440447 | C7: 0.55 | D7: 0.75 | E7: =AVERAGE(C7:D7) -> 0.65 | F7: =IF(B7>E7,"Above Peer Avg","Below Peer Avg") -> Above Peer Avg
A8: Inventory Turnover | B8: ='Ratio Analysis'!C14 -> 7.0967005 | C8: 8.06 | D8: 6.95 | E8: =AVERAGE(C8:D8) -> 7.505 | F8: =IF(B8>E8,"Above Peer Avg","Below Peer Avg") -> Below Peer Avg
A9: Return on Equity (ROE) | B9: ='Ratio Analysis'!C10 -> 0.091859688 | C9: 0.1572 | D9: 0.0965 | E9: =AVERAGE(C9:D9) -> 0.12685 | F9: =IF(B9>E9,"Above Peer Avg","Below Peer Avg") -> Below Peer Avg
A10: Return on Assets (ROA) | B10: ='Ratio Analysis'!C11 -> 0.052008669 | C10: 0.0474 | D10: 0.0366 | E10: =AVERAGE(C10:D10) -> 0.042 | F10: =IF(B10>E10,"Above Peer Avg","Below Peer Avg") -> Above Peer Avg
A11: Debt-to-Equity | B11: ='Ratio Analysis'!C20 -> 0.71604077 | C11: 1.04 | D11: 0.78 | E11: =AVERAGE(C11:D11) -> 0.91 | F11: =IF(B11>E11,"Above Peer Avg","Below Peer Avg") -> Below Peer Avg
A13: Data Sources
A14: Suzuki: Calculated in this workbook from consolidated financial statements (FY2024).
A15: Toyota & Honda: StockAnalysis.com, fiscal year ended March 31, 2024, sourced from company SEC/EDINET filings.
A16: Note: Debt-to-Equity for Toyota/Honda reflects total debt / equity (per StockAnalysis.com methodology); Suzuki figure uses total liabilities / equity as calculated in the Ratio Analysis sheet — figures are directionally, not precisely, comparable.

Sheet Common-Size Analysis
A1: Common-Size (Vertical) Analysis
A2: Balance Sheet items as % of Total Assets; Income Statement items as % of Revenue.
A4: Balance Sheet (% of Total Assets)
A5: Line Item | B5: FY2024 | C5: FY2023
A6: Cash on Hand | B6: ='Balance Sheet'!B6/'Balance Sheet'!$B$20 -> 0.19578642 | C6: ='Balance Sheet'!C6/'Balance Sheet'!$C$20 -> 0.21929049
A7: Receivables | B7: ='Balance Sheet'!B7/'Balance Sheet'!$B$20 -> 0.10375186 | C7: ='Balance Sheet'!C7/'Balance Sheet'!$C$20 -> 0.10570954
A8: Inventory | B8: ='Balance Sheet'!B8/'Balance Sheet'!$B$20 -> 0.109878 | C8: ='Balance Sheet'!C8/'Balance Sheet'!$C$20 -> 0.10602514
A9: Total Current Assets | B9: ='Balance Sheet'!B11/'Balance Sheet'!$B$20 -> 0.45261979 | C9: ='Balance Sheet'!C11/'Balance Sheet'!$C$20 -> 0.47808094
A10: Property, Plant & Equipment | B10: ='Balance Sheet'!B14/'Balance Sheet'!$B$20 -> 0.24692427 | C10: ='Balance Sheet'!C14/'Balance Sheet'!$C$20 -> 0.24783133
A11: Total Long-Term Assets | B11: ='Balance Sheet'!B18/'Balance Sheet'!$B$20 -> 0.5473794 | C11: ='Balance Sheet'!C18/'Balance Sheet'!$C$20 -> 0.52191759
A12: Total Assets | B12: ='Balance Sheet'!B20/'Balance Sheet'!$B$20 -> 1 | C12: ='Balance Sheet'!C20/'Balance Sheet'!$C$20 -> 1
A13: Total Current Liabilities | B13: ='Balance Sheet'!B22/'Balance Sheet'!$B$20 -> 0.32327694 | C13: ='Balance Sheet'!C22/'Balance Sheet'!$C$20 -> 0.32493001
A14: Total Liabilities | B14: ='Balance Sheet'!B26/'Balance Sheet'!$B$20 -> 0.41726315 | C14: ='Balance Sheet'!C26/'Balance Sheet'!$C$20 -> 0.45199244
A15: Total Shareholders Equity | B15: ='Balance Sheet'!B32/'Balance Sheet'!$B$20 -> 0.58273658 | C15: ='Balance Sheet'!C32/'Balance Sheet'!$C$20 -> 0.54800727
A18: Income Statement (% of Revenue)
A19: Line Item | B19: FY2024 | C19: FY2023
A20: Cost of Goods Sold | B20: ='Income Statement'!B6/'Income Statement'!$B$5 -> 0.73438649 | C20: ='Income Statement'!C6/'Income Statement'!$C$5 -> 0.74641916
A21: Gross Profit | B21: ='Income Statement'!B7/'Income Statement'!$B$5 -> 0.26561324 | C21: ='Income Statement'!C7/'Income Statement'!$C$5 -> 0.25356512
A22: SG&A Expenses | B22: ='Income Statement'!B9/'Income Statement'!$B$5 -> 0.13610887 | C22: ='Income Statement'!C9/'Income Statement'!$C$5 -> 0.14997642
A23: Operating Income | B23: ='Income Statement'!B12/'Income Statement'!$B$5 -> 0.10793074 | C23: ='Income Statement'!C12/'Income Statement'!$C$5 -> 0.081176251
A24: Net Income | B24: ='Income Statement'!B18/'Income Statement'!$B$5 -> 0.049814602 | C24: ='Income Statement'!C18/'Income Statement'!$C$5 -> 0.04763
A25: EBITDA | B25: ='Income Statement'!B19/'Income Statement'!$B$5 -> 0.14462703 | C25: ='Income Statement'!C19/'Income Statement'!$C$5 -> 0.11937013

Sheet Balance Sheet
A1: Suzuki Motor Corporation — Consolidated Balance Sheet
A2: (in $ millions, unless otherwise noted)
A4: Particulars | B4: FY2024 (Mar 31, 2024) | C4: FY2023 (Mar 31, 2023)
A5: Current Assets
A6: Cash on Hand | B6: 7275.574 | C6: 7428.483
A7: Receivables | B7: 3855.499 | C7: 3580.919
A8: Inventory | B8: 4083.151 | C8: 3591.61
A9: Prepaid Expenses | B9: 0 | C9: 0
A10: Other Current Assets | B10: 1605.458 | C10: 1594.278
A11: Total Current Assets | B11: 16819.7 | C11: 16195.03
A13: Long-Term Assets
A14: Property, Plant & Equipment | B14: 9175.896 | C14: 8395.306
A15: Long-Term Investments | B15: 9674.207 | C15: 7734.99
A16: Goodwill and Intangible Assets | B16: 53.848 | C16: 28.409
A17: Other Long-Term Assets | B17: 840.558 | C17: 618.648
A18: Total Long-Term Assets | B18: 20341.04 | C18: 17680
A20: Total Assets | B20: 37160.77 | C20: 33875.08
A22: Current Liabilities | B22: 12013.22 | C22: 11007.03
A23: Long-Term Debt | B23: 2272.867 | C23: 3084.224
A24: Other Non-Current Liabilities | B24: 778.058 | C24: 674.616
A25: Other Long-Term Liabilities | B25: 442.873 | C25: 545.41
A26: Total Liabilities | B26: 15505.82 | C26: 15311.28
A28: Common Stock Net | B28: 954.753 | C28: 1023.71
... A34: Total Liabilities & Shareholders Equity | B34: 37160.77 | C34: 33875.08

Sheet Income Statement
A1: Suzuki Motor Corporation — Consolidated Income Statement
A2: (in $ millions, unless otherwise noted)
A4: Particulars | B4: FY2024 (Mar 31, 2024) | C4: FY2023 (Mar 31, 2023)
A5: Revenue | B5: 37082.3 | C5: 34348.1
A6: Cost of Goods Sold | B6: 27232.74 | C6: 25638.08
A7: Gross Profit | B7: 9849.55 | C7: 8709.48
A8: Research & Development Expenses | B8: 0.799 | C8: 0.769
A9: SG&A Expenses | B9: 5047.23 | C9: 5151.405
A10: Other Operating Income/Expenses | B10: 0 | C10: 0
A11: Operating Expenses | B11: 5847.23 | C11: 5921.23
A12: Operating Income | B12: 4002.32 | C12: 2788.25
A13: Total Non-Operating Income/Expense | B13: 0.226 | C13: 0.248
A14: Pre-Tax Income | B14: 4228.57 | C14: 3036.57
A15: Income Taxes | B15: 1000.88 | C15: 709.07
A16: Income After Taxes | B16: 3227.69 | C16: 2327.5
... A18: Net Income | B18: 1847.24 | C18: 1636
A19: EBITDA | B19: =B12+'Cash Flow Statement'!B6 -> 5363.103 | C19: =C12+'Cash Flow Statement'!C6 -> 4100.137
A20: EBIT | B20: =B12 -> 4002.32 | C20: =C12 -> 2788.25
A21: Shares Outstanding (millions) | B21: 484 | C21: 484
A22: EPS (Reported) | B22: 3.82 | C22: 3.37

Sheet Cash Flow Statement
A1: Suzuki Motor Corporation — Consolidated Statement of Cash Flows
A2: (in $ millions, unless otherwise noted)
A4: Particulars | B4: FY2024 (Mar 31, 2024) | C4: FY2023 (Mar 31, 2023)
A5: Net Income | B5: 1847.24 | C5: 1636
A6: Depreciation & Amortization | B6: 1360.783 | C6: 1311.887
A7: Other Non-Cash Items | B7: 806.527 | C7: 1090.252
A8: Change in Accounts Receivable | B8: -117.825 | C8: -248.158
A9: Change in Inventories | B9: -355.656 | C9: -849.187
A10: Change in Accounts Payable | B10: 378.511 | C10: 160.371
A11: Other Changes in Assets/Liabilities | B11: 90.874 | C11: 322.607
A12: Cash Flow from Operating Activities | B12: 6550.455 | C12: 5957.575
A13: Net Change in Property, Plant & Equipment | B13: -2066.743 | C13: -2191.055
A14: Net Change in Short-Term Investments | B14: -251.878 | C14: 536.019
A15: Net Change in Long-Term Investments | B15: -8285.046 | C15: -284.514
A16: Investing Activities - Other | B16: -1198.324 | C16: -1238.738
... A24: Net Change in Cash | B24: -196.705 | C24: 178.717

Sheet Notes & Sources
A1: Notes, Assumptions & Data Sources
A3: Data Source (Suzuki) | B3: Suzuki Motor Corporation's consolidated Balance Sheet, Income Statement, and Cash Flow Statement, FY2023 (year ended Mar 31, 2023) and FY2024 (year ended Mar 31, 2024).
A4: Data Source (Peers) | B4: Toyota and Honda FY2024 (year ended Mar 31, 2024) ratios sourced from StockAnalysis.com, compiled from company SEC/EDINET filings.
A5: Currency | B5: All figures presented in $ millions unless otherwise stated.
A6: Averaging Methodology | B6: Ratios requiring average balances (ROE, ROA, Asset Turnover, Inventory Turnover, Equity Multiplier) use the average of FY2023 and FY2024 period-end balances, standard financial analysis convention.
A7: FY2023 Limitation | B7: FY2023 average-balance ratios are not shown, as they would require FY2022 balance sheet data outside the scope of this dataset.
A8: Peer Comparability | B8: Debt-to-Equity methodology may differ slightly between Suzuki (total liabilities / equity, calculated in this workbook) and Toyota/Honda (total debt / equity, per StockAnalysis.com) — comparisons are directional, not exact.
A9: Analysis Date | B9: July 2026.
A10: Purpose | B10: This model was built for independent educational and portfolio purposes, applying financial statement analysis techniques to publicly available data.
A12: Data Correction Log
A13: The originally sourced Net Income figures ($5,847.24M FY2024 / $4,356.55M FY2023) did not reconcile with EPS x Shares Outstanding ($3.82 x 484M = $1,849M implied). Cross-checked against independently reported figures (MacroTrends), corrected Net Income of $1,847.24M (FY2024) and $1,636.00M (FY2023) was used throughout this model. EBITDA and EBIT were recalculated accordingly as Operating Income + D&A and Operating Income, respectively.
